bighudders/__init__.py
bighudders/program.py
bighudders-0.0.2.dist-info/METADATA
bighudders-0.0.2.dist-info/WHEEL
bighudders-0.0.2.dist-info/top_level.txt
bighudders-0.0.2.dist-info/RECORD
