Metadata-Version: 2.1
Name: bighudders
Version: 0.0.2
Summary: Myles is amazing
Home-page: UNKNOWN
Author: Edward Hardy
Author-email: <hardyedward18@gmail.com>
License: UNKNOWN
Keywords: python
Platform: UNKNOWN
Classifier: Development Status :: 3 - Alpha
Classifier: Intended Audience :: Education
Classifier: Programming Language :: Python :: 3
Classifier: Operating System :: Microsoft :: Windows
Requires-Dist: pillow
